wagtail_modeladmin/__init__.py
wagtail_modeladmin/apps.py
wagtail_modeladmin/forms.py
wagtail_modeladmin/menus.py
wagtail_modeladmin/mixins.py
wagtail_modeladmin/options.py
wagtail_modeladmin/views.py
wagtail_modeladmin/wagtail_hooks.py
wagtail_modeladmin/helpers/__init__.py
wagtail_modeladmin/helpers/button.py
wagtail_modeladmin/helpers/permission.py
wagtail_modeladmin/helpers/search.py
wagtail_modeladmin/helpers/url.py
wagtail_modeladmin/locale/af/LC_MESSAGES/django.mo
wagtail_modeladmin/locale/af/LC_MESSAGES/django.po
wagtail_modeladmin/locale/ar/LC_MESSAGES/django.mo
wagtail_modeladmin/locale/ar/LC_MESSAGES/django.po
wagtail_modeladmin/locale/az_AZ/LC_MESSAGES/django.mo
wagtail_modeladmin/locale/az_AZ/LC_MESSAGES/django.po
wagtail_modeladmin/locale/be/LC_MESSAGES/django.mo
wagtail_modeladmin/locale/be/LC_MESSAGES/django.po
wagtail_modeladmin/locale/bg/LC_MESSAGES/django.mo
wagtail_modeladmin/locale/bg/LC_MESSAGES/django.po
wagtail_modeladmin/locale/bn/LC_MESSAGES/django.mo
wagtail_modeladmin/locale/bn/LC_MESSAGES/django.po
wagtail_modeladmin/locale/ca/LC_MESSAGES/django.mo
wagtail_modeladmin/locale/ca/LC_MESSAGES/django.po
wagtail_modeladmin/locale/cs/LC_MESSAGES/django.mo
wagtail_modeladmin/locale/cs/LC_MESSAGES/django.po
wagtail_modeladmin/locale/cy/LC_MESSAGES/django.mo
wagtail_modeladmin/locale/cy/LC_MESSAGES/django.po
wagtail_modeladmin/locale/da/LC_MESSAGES/django.mo
wagtail_modeladmin/locale/da/LC_MESSAGES/django.po
wagtail_modeladmin/locale/de/LC_MESSAGES/django.mo
wagtail_modeladmin/locale/de/LC_MESSAGES/django.po
wagtail_modeladmin/locale/el/LC_MESSAGES/django.mo
wagtail_modeladmin/locale/el/LC_MESSAGES/django.po
wagtail_modeladmin/locale/en/LC_MESSAGES/django.mo
wagtail_modeladmin/locale/en/LC_MESSAGES/django.po
wagtail_modeladmin/locale/es/LC_MESSAGES/django.mo
wagtail_modeladmin/locale/es/LC_MESSAGES/django.po
wagtail_modeladmin/locale/et/LC_MESSAGES/django.mo
wagtail_modeladmin/locale/et/LC_MESSAGES/django.po
wagtail_modeladmin-2.2.0.dist-info/licenses/LICENSE
wagtail_modeladmin-2.2.0.dist-info/WHEEL
wagtail_modeladmin-2.2.0.dist-info/METADATA
wagtail_modeladmin-2.2.0.dist-info/RECORD
