Metadata-Version: 2.4
Name: wagtail-modeladmin
Version: 2.2.0
Summary: Add any model in your project to the Wagtail admin. Formerly wagtail.contrib.modeladmin.
Author-email: Wagtail Core Team <hello@wagtail.org>
Requires-Python: >=3.8
Classifier: Development Status :: 5 - Production/Stable
Classifier: Intended Audience :: Developers
Classifier: License :: OSI Approved :: BSD License
Classifier: Operating System :: OS Independent
Classifier: Programming Language :: Python
Classifier: Programming Language :: Python :: 3
Classifier: Programming Language :: Python :: 3.9
Classifier: Programming Language :: Python :: 3.10
Classifier: Programming Language :: Python :: 3.11
Classifier: Programming Language :: Python :: 3.12
Classifier: Programming Language :: Python :: 3.13
Classifier: Framework :: Django
Classifier: Framework :: Django :: 4.2
Classifier: Framework :: Django :: 5.0
Classifier: Framework :: Django :: 5.1
Classifier: Framework :: Django :: 5.2
Classifier: Framework :: Wagtail
Classifier: Framework :: Wagtail :: 5
Classifier: Framework :: Wagtail :: 6
Classifier: Framework :: Wagtail :: 7
License-File: LICENSE
Requires-Dist: Wagtail>=5.2
Requires-Dist: pyenchant>=3.1.1,<4 ; extra == "docs"
Requires-Dist: myst_parser>=0.18.1,<1.0 ; extra == "docs"
Requires-Dist: Sphinx>=6.0 ; extra == "docs"
Requires-Dist: sphinx-autobuild>=0.6.0 ; extra == "docs"
Requires-Dist: sphinx-wagtail-theme==6.3.0 ; extra == "docs"
Requires-Dist: sphinxcontrib-spelling>=8.0,<9.0 ; extra == "docs"
Requires-Dist: sphinx_copybutton>=0.5 ; extra == "docs"
Requires-Dist: dj-database-url>=2.0.0 ; extra == "testing"
Requires-Dist: pre-commit<3.0 ; extra == "testing"
Project-URL: Home, https://github.com/wagtail-nest/wagtail-modeladmin
Provides-Extra: docs
Provides-Extra: testing
